wakeonlan.py
wakeonlan-2.0.0.dist-info/entry_points.txt
wakeonlan-2.0.0.dist-info/LICENSE
wakeonlan-2.0.0.dist-info/WHEEL
wakeonlan-2.0.0.dist-info/METADATA
wakeonlan-2.0.0.dist-info/RECORD
