Metadata-Version: 2.1
Name: wakeonlan
Version: 2.0.0
Summary: A small python module for wake on lan.
Home-page: https://github.com/remcohaszing/pywakeonlan
License: MIT
Author: Remco Haszing
Author-email: remcohaszing@gmail.com
Requires-Python: >=3.6,<4.0
Classifier: Development Status :: 5 - Production/Stable
Classifier: Intended Audience :: Developers
Classifier: Intended Audience :: System Administrators
Classifier: License :: OSI Approved :: MIT License
Classifier: Programming Language :: Python :: 3
Classifier: Programming Language :: Python :: 3.6
Classifier: Programming Language :: Python :: 3.7
Classifier: Programming Language :: Python :: 3.8
Classifier: Programming Language :: Python :: 3.9
Classifier: Topic :: System :: Networking
Project-URL: Documentation, http://pywakeonlan.readthedocs.io
Project-URL: Repository, https://github.com/remcohaszing/pywakeonlan
